{"routeName":"903 - Floresta","routeDesc":"","directions":[{"directionId":0,"directionDesc":"Ida","calendars":[{"serviceId":20663,"serviceDesc":"Dia útil","departures":[{"routeId":46717,"tripShortName":"Sentido para Floresta","tripId":145071,"tripName":"Sentido para Floresta","departure":"08:10:00","tripSeq":1},{"routeId":46717,"tripShortName":"Sentido para Floresta","tripId":145071,"tripName":"Sentido para Floresta","departure":"10:00:00","tripSeq":1},{"routeId":46717,"tripShortName":"Sentido para Floresta","tripId":145071,"tripName":"Sentido para Floresta","departure":"12:20:00","tripSeq":1},{"routeId":46717,"tripShortName":"Sentido para Floresta","tripId":145071,"tripName":"Sentido para Floresta","departure":"15:00:00","tripSeq":1},{"routeId":46717,"tripShortName":"Sentido para Floresta","tripId":145071,"tripName":"Sentido para Floresta","departure":"17:30:00","tripSeq":1},{"routeId":46717,"tripShortName":"Sentido para Floresta","tripId":145071,"tripName":"Sentido para Floresta","departure":"18:30:00","tripSeq":1}]},{"serviceId":20664,"serviceDesc":"Sábado","departures":[{"routeId":46717,"tripShortName":"Sentido para Floresta","tripId":145071,"tripName":"Sentido para Floresta","departure":"08:00:00","tripSeq":1},{"routeId":46717,"tripShortName":"Sentido para Floresta","tripId":145071,"tripName":"Sentido para Floresta","departure":"09:40:00","tripSeq":1},{"routeId":46717,"tripShortName":"Sentido para Floresta","tripId":145071,"tripName":"Sentido para Floresta","departure":"12:30:00","tripSeq":1},{"routeId":46717,"tripShortName":"Sentido para Floresta","tripId":145071,"tripName":"Sentido para Floresta","departure":"15:30:00","tripSeq":1},{"routeId":46717,"tripShortName":"Sentido para Floresta","tripId":145071,"tripName":"Sentido para Floresta","departure":"17:30:00","tripSeq":1}]},{"serviceId":20665,"serviceDesc":"Domingos/Feriados","departures":[{"routeId":46717,"tripShortName":"Sentido para Floresta","tripId":145071,"tripName":"Sentido para Floresta","departure":"10:20:00","tripSeq":1},{"routeId":46717,"tripShortName":"Sentido para Floresta","tripId":145071,"tripName":"Sentido para Floresta","departure":"15:50:00","tripSeq":1}]}]},{"directionId":1,"directionDesc":"Volta","calendars":[{"serviceId":20663,"serviceDesc":"Dia útil","departures":[{"routeId":46717,"tripShortName":"Sentido para Maringá","tripId":145072,"tripName":"Sentido para Maringá","departure":"06:00:00","tripSeq":2},{"routeId":46717,"tripShortName":"Sentido para Maringá","tripId":145072,"tripName":"Sentido para Maringá","departure":"07:00:00","tripSeq":2},{"routeId":46717,"tripShortName":"Sentido para Maringá","tripId":145072,"tripName":"Sentido para Maringá","departure":"07:05:00","tripSeq":2},{"routeId":46717,"tripShortName":"Sentido para Maringá","tripId":145072,"tripName":"Sentido para Maringá","departure":"09:10:00","tripSeq":2},{"routeId":46717,"tripShortName":"Sentido para Maringá","tripId":145072,"tripName":"Sentido para Maringá","departure":"11:00:00","tripSeq":2},{"routeId":46717,"tripShortName":"Sentido para Maringá","tripId":145072,"tripName":"Sentido para Maringá","departure":"13:20:00","tripSeq":2},{"routeId":46717,"tripShortName":"Sentido para Maringá","tripId":145072,"tripName":"Sentido para Maringá","departure":"16:30:00","tripSeq":2}]},{"serviceId":20664,"serviceDesc":"Sábado","departures":[{"routeId":46717,"tripShortName":"Sentido para Maringá","tripId":145072,"tripName":"Sentido para Maringá","departure":"06:00:00","tripSeq":2},{"routeId":46717,"tripShortName":"Sentido para Maringá","tripId":145072,"tripName":"Sentido para Maringá","departure":"07:00:00","tripSeq":2},{"routeId":46717,"tripShortName":"Sentido para Maringá","tripId":145072,"tripName":"Sentido para Maringá","departure":"09:00:00","tripSeq":2},{"routeId":46717,"tripShortName":"Sentido para Maringá","tripId":145072,"tripName":"Sentido para Maringá","departure":"11:00:00","tripSeq":2},{"routeId":46717,"tripShortName":"Sentido para Maringá","tripId":145072,"tripName":"Sentido para Maringá","departure":"14:20:00","tripSeq":2},{"routeId":46717,"tripShortName":"Sentido para Maringá","tripId":145072,"tripName":"Sentido para Maringá","departure":"16:30:00","tripSeq":2}]},{"serviceId":20665,"serviceDesc":"Domingos/Feriados","departures":[{"routeId":46717,"tripShortName":"Sentido para Maringá","tripId":145072,"tripName":"Sentido para Maringá","departure":"07:30:00","tripSeq":2},{"routeId":46717,"tripShortName":"Sentido para Maringá","tripId":145072,"tripName":"Sentido para Maringá","departure":"11:30:00","tripSeq":2},{"routeId":46717,"tripShortName":"Sentido para Maringá","tripId":145072,"tripName":"Sentido para Maringá","departure":"17:00:00","tripSeq":2}]}]}],"trips":[{"tripDesc":"Sentido para Maringá","tripShortName":"","directionId":1,"tripSeq":2},{"tripDesc":"Sentido para Floresta","tripShortName":"","directionId":0,"tripSeq":1}],"routes":null,"note":null}