{"routeName":"162 - Cj. Léa Leal","routeDesc":null,"directions":[{"directionId":0,"directionDesc":"Ida","calendars":[{"serviceId":1073,"serviceDesc":"Dias Úteis","departures":[{"routeId":13355,"tripShortName":"Sentido para Bairro / Cj. Léa Leal","tripId":46709,"tripName":"Sentido para Bairro / Cj. Léa Leal","departure":"06:30:00","tripSeq":1},{"routeId":13355,"tripShortName":"Sentido para Bairro / Cj. Léa Leal","tripId":46709,"tripName":"Sentido para Bairro / Cj. Léa Leal","departure":"07:00:00","tripSeq":1},{"routeId":13355,"tripShortName":"Sentido para Bairro / Cj. Léa Leal","tripId":46709,"tripName":"Sentido para Bairro / Cj. Léa Leal","departure":"07:30:00","tripSeq":1},{"routeId":13355,"tripShortName":"Sentido para Bairro / Cj. Léa Leal","tripId":46709,"tripName":"Sentido para Bairro / Cj. Léa Leal","departure":"08:30:00","tripSeq":1},{"routeId":13355,"tripShortName":"Sentido para Bairro / Cj. Léa Leal","tripId":46709,"tripName":"Sentido para Bairro / Cj. Léa Leal","departure":"09:30:00","tripSeq":1},{"routeId":13355,"tripShortName":"Sentido para Bairro / Cj. Léa Leal","tripId":46709,"tripName":"Sentido para Bairro / Cj. Léa Leal","departure":"10:30:00","tripSeq":1},{"routeId":13355,"tripShortName":"Sentido para Bairro / Cj. Léa Leal","tripId":46709,"tripName":"Sentido para Bairro / Cj. Léa Leal","departure":"11:00:00","tripSeq":1},{"routeId":13355,"tripShortName":"Sentido para Bairro / Cj. Léa Leal","tripId":46709,"tripName":"Sentido para Bairro / Cj. Léa Leal","departure":"11:30:00","tripSeq":1},{"routeId":13355,"tripShortName":"Sentido para Bairro / Cj. Léa Leal","tripId":46709,"tripName":"Sentido para Bairro / Cj. Léa Leal","departure":"12:00:00","tripSeq":1},{"routeId":13355,"tripShortName":"Sentido para Bairro / Cj. Léa Leal","tripId":46709,"tripName":"Sentido para Bairro / Cj. Léa Leal","departure":"12:30:00","tripSeq":1},{"routeId":13355,"tripShortName":"Sentido para Bairro / Cj. Léa Leal","tripId":46709,"tripName":"Sentido para Bairro / Cj. Léa Leal","departure":"13:30:00","tripSeq":1},{"routeId":13355,"tripShortName":"Sentido para Bairro / Cj. Léa Leal","tripId":46709,"tripName":"Sentido para Bairro / Cj. Léa Leal","departure":"14:30:00","tripSeq":1},{"routeId":13355,"tripShortName":"Sentido para Bairro / Cj. Léa Leal","tripId":46709,"tripName":"Sentido para Bairro / Cj. Léa Leal","departure":"15:30:00","tripSeq":1},{"routeId":13355,"tripShortName":"Sentido para Bairro / Cj. Léa Leal","tripId":46709,"tripName":"Sentido para Bairro / Cj. Léa Leal","departure":"16:30:00","tripSeq":1},{"routeId":13355,"tripShortName":"Sentido para Bairro / Cj. Léa Leal","tripId":46709,"tripName":"Sentido para Bairro / Cj. Léa Leal","departure":"17:30:00","tripSeq":1},{"routeId":13355,"tripShortName":"Sentido para Bairro / Cj. Léa Leal","tripId":46709,"tripName":"Sentido para Bairro / Cj. Léa Leal","departure":"18:13:00","tripSeq":1},{"routeId":13355,"tripShortName":"Sentido para Bairro / Cj. Léa Leal","tripId":46709,"tripName":"Sentido para Bairro / Cj. Léa Leal","departure":"18:30:00","tripSeq":1},{"routeId":13355,"tripShortName":"Sentido para Bairro / Cj. Léa Leal","tripId":46709,"tripName":"Sentido para Bairro / Cj. Léa Leal","departure":"19:10:00","tripSeq":1},{"routeId":13355,"tripShortName":"Sentido para Bairro / Cj. Léa Leal","tripId":46709,"tripName":"Sentido para Bairro / Cj. Léa Leal","departure":"19:30:00","tripSeq":1},{"routeId":13355,"tripShortName":"Sentido para Bairro / Cj. Léa Leal","tripId":46709,"tripName":"Sentido para Bairro / Cj. Léa Leal","departure":"20:30:00","tripSeq":1},{"routeId":13355,"tripShortName":"Sentido para Bairro / Cj. Léa Leal","tripId":46709,"tripName":"Sentido para Bairro / Cj. Léa Leal","departure":"21:30:00","tripSeq":1},{"routeId":13355,"tripShortName":"Sentido para Bairro / Cj. Léa Leal","tripId":46709,"tripName":"Sentido para Bairro / Cj. Léa Leal","departure":"22:30:00","tripSeq":1},{"routeId":13355,"tripShortName":"Sentido para Bairro / Cj. Léa Leal","tripId":46709,"tripName":"Sentido para Bairro / Cj. Léa Leal","departure":"23:30:00","tripSeq":1}]},{"serviceId":1079,"serviceDesc":"Sábados","departures":[{"routeId":13355,"tripShortName":"Sentido para Bairro / Cj. Léa Leal","tripId":46709,"tripName":"Sentido para Bairro / Cj. Léa Leal","departure":"06:30:00","tripSeq":1},{"routeId":13355,"tripShortName":"Sentido para Bairro / Cj. Léa Leal","tripId":46709,"tripName":"Sentido para Bairro / Cj. Léa Leal","departure":"07:30:00","tripSeq":1},{"routeId":13355,"tripShortName":"Sentido para Bairro / Cj. Léa Leal","tripId":46709,"tripName":"Sentido para Bairro / Cj. Léa Leal","departure":"08:30:00","tripSeq":1},{"routeId":13355,"tripShortName":"Sentido para Bairro / Cj. Léa Leal","tripId":46709,"tripName":"Sentido para Bairro / Cj. Léa Leal","departure":"09:30:00","tripSeq":1},{"routeId":13355,"tripShortName":"Sentido para Bairro / Cj. Léa Leal","tripId":46709,"tripName":"Sentido para Bairro / Cj. Léa Leal","departure":"10:30:00","tripSeq":1},{"routeId":13355,"tripShortName":"Sentido para Bairro / Cj. Léa Leal","tripId":46709,"tripName":"Sentido para Bairro / Cj. Léa Leal","departure":"11:00:00","tripSeq":1},{"routeId":13355,"tripShortName":"Sentido para Bairro / Cj. Léa Leal","tripId":46709,"tripName":"Sentido para Bairro / Cj. Léa Leal","departure":"11:30:00","tripSeq":1},{"routeId":13355,"tripShortName":"Sentido para Bairro / Cj. Léa Leal","tripId":46709,"tripName":"Sentido para Bairro / Cj. Léa Leal","departure":"12:15:00","tripSeq":1},{"routeId":13355,"tripShortName":"Sentido para Bairro / Cj. Léa Leal","tripId":46709,"tripName":"Sentido para Bairro / Cj. Léa Leal","departure":"12:30:00","tripSeq":1},{"routeId":13355,"tripShortName":"Sentido para Bairro / Cj. Léa Leal","tripId":46709,"tripName":"Sentido para Bairro / Cj. Léa Leal","departure":"13:30:00","tripSeq":1},{"routeId":13355,"tripShortName":"Sentido para Bairro / Cj. Léa Leal","tripId":46709,"tripName":"Sentido para Bairro / Cj. Léa Leal","departure":"14:30:00","tripSeq":1},{"routeId":13355,"tripShortName":"Sentido para Bairro / Cj. Léa Leal","tripId":46709,"tripName":"Sentido para Bairro / Cj. Léa Leal","departure":"15:30:00","tripSeq":1},{"routeId":13355,"tripShortName":"Sentido para Bairro / Cj. Léa Leal","tripId":46709,"tripName":"Sentido para Bairro / Cj. Léa Leal","departure":"16:30:00","tripSeq":1},{"routeId":13355,"tripShortName":"Sentido para Bairro / Cj. Léa Leal","tripId":46709,"tripName":"Sentido para Bairro / Cj. Léa Leal","departure":"17:30:00","tripSeq":1},{"routeId":13355,"tripShortName":"Sentido para Bairro / Cj. Léa Leal","tripId":46709,"tripName":"Sentido para Bairro / Cj. Léa Leal","departure":"18:30:00","tripSeq":1},{"routeId":13355,"tripShortName":"Sentido para Bairro / Cj. Léa Leal","tripId":46709,"tripName":"Sentido para Bairro / Cj. Léa Leal","departure":"19:30:00","tripSeq":1},{"routeId":13355,"tripShortName":"Sentido para Bairro / Cj. Léa Leal","tripId":46709,"tripName":"Sentido para Bairro / Cj. Léa Leal","departure":"20:30:00","tripSeq":1},{"routeId":13355,"tripShortName":"Sentido para Bairro / Cj. Léa Leal","tripId":46709,"tripName":"Sentido para Bairro / Cj. Léa Leal","departure":"21:30:00","tripSeq":1},{"routeId":13355,"tripShortName":"Sentido para Bairro / Cj. Léa Leal","tripId":46709,"tripName":"Sentido para Bairro / Cj. Léa Leal","departure":"22:30:00","tripSeq":1},{"routeId":13355,"tripShortName":"Sentido para Bairro / Cj. Léa Leal","tripId":46709,"tripName":"Sentido para Bairro / Cj. Léa Leal","departure":"23:30:00","tripSeq":1}]},{"serviceId":1072,"serviceDesc":"Domingos/Feriados","departures":[{"routeId":13355,"tripShortName":"Sentido para Bairro / Cj. Léa Leal","tripId":46709,"tripName":"Sentido para Bairro / Cj. Léa Leal","departure":"06:30:00","tripSeq":1},{"routeId":13355,"tripShortName":"Sentido para Bairro / Cj. Léa Leal","tripId":46709,"tripName":"Sentido para Bairro / Cj. Léa Leal","departure":"07:30:00","tripSeq":1},{"routeId":13355,"tripShortName":"Sentido para Bairro / Cj. Léa Leal","tripId":46709,"tripName":"Sentido para Bairro / Cj. Léa Leal","departure":"08:30:00","tripSeq":1},{"routeId":13355,"tripShortName":"Sentido para Bairro / Cj. Léa Leal","tripId":46709,"tripName":"Sentido para Bairro / Cj. Léa Leal","departure":"09:30:00","tripSeq":1},{"routeId":13355,"tripShortName":"Sentido para Bairro / Cj. Léa Leal","tripId":46709,"tripName":"Sentido para Bairro / Cj. Léa Leal","departure":"10:30:00","tripSeq":1},{"routeId":13355,"tripShortName":"Sentido para Bairro / Cj. Léa Leal","tripId":46709,"tripName":"Sentido para Bairro / Cj. Léa Leal","departure":"11:30:00","tripSeq":1},{"routeId":13355,"tripShortName":"Sentido para Bairro / Cj. Léa Leal","tripId":46709,"tripName":"Sentido para Bairro / Cj. Léa Leal","departure":"12:30:00","tripSeq":1},{"routeId":13355,"tripShortName":"Sentido para Bairro / Cj. Léa Leal","tripId":46709,"tripName":"Sentido para Bairro / Cj. Léa Leal","departure":"13:30:00","tripSeq":1},{"routeId":13355,"tripShortName":"Sentido para Bairro / Cj. Léa Leal","tripId":46709,"tripName":"Sentido para Bairro / Cj. Léa Leal","departure":"14:30:00","tripSeq":1},{"routeId":13355,"tripShortName":"Sentido para Bairro / Cj. Léa Leal","tripId":46709,"tripName":"Sentido para Bairro / Cj. Léa Leal","departure":"15:30:00","tripSeq":1},{"routeId":13355,"tripShortName":"Sentido para Bairro / Cj. Léa Leal","tripId":46709,"tripName":"Sentido para Bairro / Cj. Léa Leal","departure":"16:30:00","tripSeq":1},{"routeId":13355,"tripShortName":"Sentido para Bairro / Cj. Léa Leal","tripId":46709,"tripName":"Sentido para Bairro / Cj. Léa Leal","departure":"17:30:00","tripSeq":1},{"routeId":13355,"tripShortName":"Sentido para Bairro / Cj. Léa Leal","tripId":46709,"tripName":"Sentido para Bairro / Cj. Léa Leal","departure":"18:30:00","tripSeq":1},{"routeId":13355,"tripShortName":"Sentido para Bairro / Cj. Léa Leal","tripId":46709,"tripName":"Sentido para Bairro / Cj. Léa Leal","departure":"19:30:00","tripSeq":1},{"routeId":13355,"tripShortName":"Sentido para Bairro / Cj. Léa Leal","tripId":46709,"tripName":"Sentido para Bairro / Cj. Léa Leal","departure":"20:30:00","tripSeq":1},{"routeId":13355,"tripShortName":"Sentido para Bairro / Cj. Léa Leal","tripId":46709,"tripName":"Sentido para Bairro / Cj. Léa Leal","departure":"21:30:00","tripSeq":1},{"routeId":13355,"tripShortName":"Sentido para Bairro / Cj. Léa Leal","tripId":46709,"tripName":"Sentido para Bairro / Cj. Léa Leal","departure":"22:30:00","tripSeq":1},{"routeId":13355,"tripShortName":"Sentido para Bairro / Cj. Léa Leal","tripId":46709,"tripName":"Sentido para Bairro / Cj. Léa Leal","departure":"23:30:00","tripSeq":1}]}]},{"directionId":1,"directionDesc":"Volta","calendars":[{"serviceId":1073,"serviceDesc":"Dias Úteis","departures":[{"routeId":13355,"tripShortName":"Sentido para Terminal","tripId":46710,"tripName":"Sentido para Terminal","departure":"06:00:00","tripSeq":2},{"routeId":13355,"tripShortName":"Sentido para Terminal","tripId":46710,"tripName":"Sentido para Terminal","departure":"06:30:00","tripSeq":2},{"routeId":13355,"tripShortName":"Sentido para Terminal","tripId":46710,"tripName":"Sentido para Terminal","departure":"07:00:00","tripSeq":2},{"routeId":13355,"tripShortName":"Sentido para Terminal","tripId":46710,"tripName":"Sentido para Terminal","departure":"07:20:00","tripSeq":2},{"routeId":13355,"tripShortName":"Sentido para Terminal","tripId":46710,"tripName":"Sentido para Terminal","departure":"08:00:00","tripSeq":2},{"routeId":13355,"tripShortName":"Sentido para Terminal","tripId":46710,"tripName":"Sentido para Terminal","departure":"09:00:00","tripSeq":2},{"routeId":13355,"tripShortName":"Sentido para Terminal","tripId":46710,"tripName":"Sentido para Terminal","departure":"10:00:00","tripSeq":2},{"routeId":13355,"tripShortName":"Sentido para Terminal","tripId":46710,"tripName":"Sentido para Terminal","departure":"11:00:00","tripSeq":2},{"routeId":13355,"tripShortName":"Sentido para Terminal","tripId":46710,"tripName":"Sentido para Terminal","departure":"11:30:00","tripSeq":2},{"routeId":13355,"tripShortName":"Sentido para Terminal","tripId":46710,"tripName":"Sentido para Terminal","departure":"12:00:00","tripSeq":2},{"routeId":13355,"tripShortName":"Sentido para Terminal","tripId":46710,"tripName":"Sentido para Terminal","departure":"12:30:00","tripSeq":2},{"routeId":13355,"tripShortName":"Sentido para Terminal","tripId":46710,"tripName":"Sentido para Terminal","departure":"13:00:00","tripSeq":2},{"routeId":13355,"tripShortName":"Sentido para Terminal","tripId":46710,"tripName":"Sentido para Terminal","departure":"14:00:00","tripSeq":2},{"routeId":13355,"tripShortName":"Sentido para Terminal","tripId":46710,"tripName":"Sentido para Terminal","departure":"15:00:00","tripSeq":2},{"routeId":13355,"tripShortName":"Sentido para Terminal","tripId":46710,"tripName":"Sentido para Terminal","departure":"16:00:00","tripSeq":2},{"routeId":13355,"tripShortName":"Sentido para Terminal","tripId":46710,"tripName":"Sentido para Terminal","departure":"17:00:00","tripSeq":2},{"routeId":13355,"tripShortName":"Sentido para Terminal","tripId":46710,"tripName":"Sentido para Terminal","departure":"18:00:00","tripSeq":2},{"routeId":13355,"tripShortName":"Sentido para Terminal","tripId":46710,"tripName":"Sentido para Terminal","departure":"18:40:00","tripSeq":2},{"routeId":13355,"tripShortName":"Sentido para Terminal","tripId":46710,"tripName":"Sentido para Terminal","departure":"19:00:00","tripSeq":2},{"routeId":13355,"tripShortName":"Sentido para Terminal","tripId":46710,"tripName":"Sentido para Terminal","departure":"20:00:00","tripSeq":2},{"routeId":13355,"tripShortName":"Sentido para Terminal","tripId":46710,"tripName":"Sentido para Terminal","departure":"21:00:00","tripSeq":2},{"routeId":13355,"tripShortName":"Sentido para Terminal","tripId":46710,"tripName":"Sentido para Terminal","departure":"22:00:00","tripSeq":2},{"routeId":13355,"tripShortName":"Sentido para Terminal","tripId":46710,"tripName":"Sentido para Terminal","departure":"23:00:00","tripSeq":2}]},{"serviceId":1079,"serviceDesc":"Sábados","departures":[{"routeId":13355,"tripShortName":"Sentido para Terminal","tripId":46710,"tripName":"Sentido para Terminal","departure":"06:00:00","tripSeq":2},{"routeId":13355,"tripShortName":"Sentido para Terminal","tripId":46710,"tripName":"Sentido para Terminal","departure":"06:30:00","tripSeq":2},{"routeId":13355,"tripShortName":"Sentido para Terminal","tripId":46710,"tripName":"Sentido para Terminal","departure":"07:00:00","tripSeq":2},{"routeId":13355,"tripShortName":"Sentido para Terminal","tripId":46710,"tripName":"Sentido para Terminal","departure":"07:20:00","tripSeq":2},{"routeId":13355,"tripShortName":"Sentido para Terminal","tripId":46710,"tripName":"Sentido para Terminal","departure":"08:00:00","tripSeq":2},{"routeId":13355,"tripShortName":"Sentido para Terminal","tripId":46710,"tripName":"Sentido para Terminal","departure":"09:00:00","tripSeq":2},{"routeId":13355,"tripShortName":"Sentido para Terminal","tripId":46710,"tripName":"Sentido para Terminal","departure":"10:00:00","tripSeq":2},{"routeId":13355,"tripShortName":"Sentido para Terminal","tripId":46710,"tripName":"Sentido para Terminal","departure":"11:00:00","tripSeq":2},{"routeId":13355,"tripShortName":"Sentido para Terminal","tripId":46710,"tripName":"Sentido para Terminal","departure":"11:30:00","tripSeq":2},{"routeId":13355,"tripShortName":"Sentido para Terminal","tripId":46710,"tripName":"Sentido para Terminal","departure":"12:00:00","tripSeq":2},{"routeId":13355,"tripShortName":"Sentido para Terminal","tripId":46710,"tripName":"Sentido para Terminal","departure":"13:00:00","tripSeq":2},{"routeId":13355,"tripShortName":"Sentido para Terminal","tripId":46710,"tripName":"Sentido para Terminal","departure":"14:00:00","tripSeq":2},{"routeId":13355,"tripShortName":"Sentido para Terminal","tripId":46710,"tripName":"Sentido para Terminal","departure":"15:00:00","tripSeq":2},{"routeId":13355,"tripShortName":"Sentido para Terminal","tripId":46710,"tripName":"Sentido para Terminal","departure":"16:00:00","tripSeq":2},{"routeId":13355,"tripShortName":"Sentido para Terminal","tripId":46710,"tripName":"Sentido para Terminal","departure":"17:00:00","tripSeq":2},{"routeId":13355,"tripShortName":"Sentido para Terminal","tripId":46710,"tripName":"Sentido para Terminal","departure":"18:00:00","tripSeq":2},{"routeId":13355,"tripShortName":"Sentido para Terminal","tripId":46710,"tripName":"Sentido para Terminal","departure":"19:00:00","tripSeq":2},{"routeId":13355,"tripShortName":"Sentido para Terminal","tripId":46710,"tripName":"Sentido para Terminal","departure":"20:00:00","tripSeq":2},{"routeId":13355,"tripShortName":"Sentido para Terminal","tripId":46710,"tripName":"Sentido para Terminal","departure":"21:00:00","tripSeq":2},{"routeId":13355,"tripShortName":"Sentido para Terminal","tripId":46710,"tripName":"Sentido para Terminal","departure":"22:00:00","tripSeq":2},{"routeId":13355,"tripShortName":"Sentido para Terminal","tripId":46710,"tripName":"Sentido para Terminal","departure":"23:00:00","tripSeq":2}]},{"serviceId":1072,"serviceDesc":"Domingos/Feriados","departures":[{"routeId":13355,"tripShortName":"Sentido para Terminal","tripId":46710,"tripName":"Sentido para Terminal","departure":"06:00:00","tripSeq":2},{"routeId":13355,"tripShortName":"Sentido para Terminal","tripId":46710,"tripName":"Sentido para Terminal","departure":"07:00:00","tripSeq":2},{"routeId":13355,"tripShortName":"Sentido para Terminal","tripId":46710,"tripName":"Sentido para Terminal","departure":"08:00:00","tripSeq":2},{"routeId":13355,"tripShortName":"Sentido para Terminal","tripId":46710,"tripName":"Sentido para Terminal","departure":"09:00:00","tripSeq":2},{"routeId":13355,"tripShortName":"Sentido para Terminal","tripId":46710,"tripName":"Sentido para Terminal","departure":"10:00:00","tripSeq":2},{"routeId":13355,"tripShortName":"Sentido para Terminal","tripId":46710,"tripName":"Sentido para Terminal","departure":"11:00:00","tripSeq":2},{"routeId":13355,"tripShortName":"Sentido para Terminal","tripId":46710,"tripName":"Sentido para Terminal","departure":"12:00:00","tripSeq":2},{"routeId":13355,"tripShortName":"Sentido para Terminal","tripId":46710,"tripName":"Sentido para Terminal","departure":"13:00:00","tripSeq":2},{"routeId":13355,"tripShortName":"Sentido para Terminal","tripId":46710,"tripName":"Sentido para Terminal","departure":"14:00:00","tripSeq":2},{"routeId":13355,"tripShortName":"Sentido para Terminal","tripId":46710,"tripName":"Sentido para Terminal","departure":"15:00:00","tripSeq":2},{"routeId":13355,"tripShortName":"Sentido para Terminal","tripId":46710,"tripName":"Sentido para Terminal","departure":"16:00:00","tripSeq":2},{"routeId":13355,"tripShortName":"Sentido para Terminal","tripId":46710,"tripName":"Sentido para Terminal","departure":"17:00:00","tripSeq":2},{"routeId":13355,"tripShortName":"Sentido para Terminal","tripId":46710,"tripName":"Sentido para Terminal","departure":"18:00:00","tripSeq":2},{"routeId":13355,"tripShortName":"Sentido para Terminal","tripId":46710,"tripName":"Sentido para Terminal","departure":"19:00:00","tripSeq":2},{"routeId":13355,"tripShortName":"Sentido para Terminal","tripId":46710,"tripName":"Sentido para Terminal","departure":"20:00:00","tripSeq":2},{"routeId":13355,"tripShortName":"Sentido para Terminal","tripId":46710,"tripName":"Sentido para Terminal","departure":"21:00:00","tripSeq":2},{"routeId":13355,"tripShortName":"Sentido para Terminal","tripId":46710,"tripName":"Sentido para Terminal","departure":"22:00:00","tripSeq":2},{"routeId":13355,"tripShortName":"Sentido para Terminal","tripId":46710,"tripName":"Sentido para Terminal","departure":"23:00:00","tripSeq":2}]}]}],"trips":[{"tripDesc":"Sentido para Bairro / Cj. Léa Leal","tripShortName":null,"directionId":0,"tripSeq":1},{"tripDesc":"Sentido para Terminal","tripShortName":null,"directionId":1,"tripSeq":2}],"routes":null,"note":null}