{"routeName":"175 - Jd. Sumaré","routeDesc":null,"directions":[{"directionId":0,"directionDesc":"Ida","calendars":[{"serviceId":1073,"serviceDesc":"Dias Úteis","departures":[{"routeId":13398,"tripShortName":"Sentido para Bairro / Jd. Sumaré","tripId":46778,"tripName":"Sentido para Bairro / Jd. Sumaré","departure":"06:25:00","tripSeq":1},{"routeId":13398,"tripShortName":"Sentido para Bairro / Jd. Sumaré","tripId":46778,"tripName":"Sentido para Bairro / Jd. Sumaré","departure":"07:00:00","tripSeq":1},{"routeId":13398,"tripShortName":"Sentido para Bairro / Jd. Sumaré","tripId":46778,"tripName":"Sentido para Bairro / Jd. Sumaré","departure":"07:35:00","tripSeq":1},{"routeId":13398,"tripShortName":"Sentido para Bairro / Jd. Sumaré","tripId":46778,"tripName":"Sentido para Bairro / Jd. Sumaré","departure":"08:50:00","tripSeq":1},{"routeId":13398,"tripShortName":"Sentido para Bairro / Jd. Sumaré","tripId":46778,"tripName":"Sentido para Bairro / Jd. Sumaré","departure":"10:00:00","tripSeq":1},{"routeId":13398,"tripShortName":"Sentido para Bairro / Jd. Sumaré","tripId":46778,"tripName":"Sentido para Bairro / Jd. Sumaré","departure":"10:30:00","tripSeq":1},{"routeId":13398,"tripShortName":"Sentido para Bairro / Jd. Sumaré","tripId":46778,"tripName":"Sentido para Bairro / Jd. Sumaré","departure":"11:10:00","tripSeq":1},{"routeId":13398,"tripShortName":"Sentido para Bairro / Jd. Sumaré","tripId":46778,"tripName":"Sentido para Bairro / Jd. Sumaré","departure":"11:40:00","tripSeq":1},{"routeId":13398,"tripShortName":"Sentido para Bairro / Jd. Sumaré","tripId":46778,"tripName":"Sentido para Bairro / Jd. Sumaré","departure":"12:20:00","tripSeq":1},{"routeId":13398,"tripShortName":"Sentido para Bairro / Jd. Sumaré","tripId":46778,"tripName":"Sentido para Bairro / Jd. Sumaré","departure":"13:30:00","tripSeq":1},{"routeId":13398,"tripShortName":"Sentido para Bairro / Jd. Sumaré","tripId":46778,"tripName":"Sentido para Bairro / Jd. Sumaré","departure":"14:40:00","tripSeq":1},{"routeId":13398,"tripShortName":"Sentido para Bairro / Jd. Sumaré","tripId":46778,"tripName":"Sentido para Bairro / Jd. Sumaré","departure":"15:50:00","tripSeq":1},{"routeId":13398,"tripShortName":"Sentido para Bairro / Jd. Sumaré","tripId":46778,"tripName":"Sentido para Bairro / Jd. Sumaré","departure":"17:00:00","tripSeq":1},{"routeId":13398,"tripShortName":"Sentido para Bairro / Jd. Sumaré","tripId":46778,"tripName":"Sentido para Bairro / Jd. Sumaré","departure":"17:30:00","tripSeq":1},{"routeId":13398,"tripShortName":"Sentido para Bairro / Jd. Sumaré","tripId":46778,"tripName":"Sentido para Bairro / Jd. Sumaré","departure":"18:10:00","tripSeq":1},{"routeId":13398,"tripShortName":"Sentido para Bairro / Jd. Sumaré","tripId":46778,"tripName":"Sentido para Bairro / Jd. Sumaré","departure":"18:45:00","tripSeq":1},{"routeId":13398,"tripShortName":"Sentido para Bairro / Jd. Sumaré","tripId":46778,"tripName":"Sentido para Bairro / Jd. Sumaré","departure":"19:20:00","tripSeq":1},{"routeId":13398,"tripShortName":"Sentido para Bairro / Jd. Sumaré","tripId":46778,"tripName":"Sentido para Bairro / Jd. Sumaré","departure":"20:30:00","tripSeq":1},{"routeId":13398,"tripShortName":"Sentido para Bairro / Jd. Sumaré","tripId":46778,"tripName":"Sentido para Bairro / Jd. Sumaré","departure":"21:30:00","tripSeq":1},{"routeId":13398,"tripShortName":"Sentido para Bairro / Jd. Sumaré","tripId":46778,"tripName":"Sentido para Bairro / Jd. Sumaré","departure":"22:30:00","tripSeq":1},{"routeId":13398,"tripShortName":"Sentido para Bairro / Jd. Sumaré","tripId":46778,"tripName":"Sentido para Bairro / Jd. Sumaré","departure":"23:30:00","tripSeq":1}]},{"serviceId":1079,"serviceDesc":"Sábados","departures":[{"routeId":13398,"tripShortName":"Sentido para Bairro / Jd. Sumaré","tripId":46778,"tripName":"Sentido para Bairro / Jd. Sumaré","departure":"06:25:00","tripSeq":1},{"routeId":13398,"tripShortName":"Sentido para Bairro / Jd. Sumaré","tripId":46778,"tripName":"Sentido para Bairro / Jd. Sumaré","departure":"07:00:00","tripSeq":1},{"routeId":13398,"tripShortName":"Sentido para Bairro / Jd. Sumaré","tripId":46778,"tripName":"Sentido para Bairro / Jd. Sumaré","departure":"07:35:00","tripSeq":1},{"routeId":13398,"tripShortName":"Sentido para Bairro / Jd. Sumaré","tripId":46778,"tripName":"Sentido para Bairro / Jd. Sumaré","departure":"08:45:00","tripSeq":1},{"routeId":13398,"tripShortName":"Sentido para Bairro / Jd. Sumaré","tripId":46778,"tripName":"Sentido para Bairro / Jd. Sumaré","departure":"09:55:00","tripSeq":1},{"routeId":13398,"tripShortName":"Sentido para Bairro / Jd. Sumaré","tripId":46778,"tripName":"Sentido para Bairro / Jd. Sumaré","departure":"10:30:00","tripSeq":1},{"routeId":13398,"tripShortName":"Sentido para Bairro / Jd. Sumaré","tripId":46778,"tripName":"Sentido para Bairro / Jd. Sumaré","departure":"11:05:00","tripSeq":1},{"routeId":13398,"tripShortName":"Sentido para Bairro / Jd. Sumaré","tripId":46778,"tripName":"Sentido para Bairro / Jd. Sumaré","departure":"11:40:00","tripSeq":1},{"routeId":13398,"tripShortName":"Sentido para Bairro / Jd. Sumaré","tripId":46778,"tripName":"Sentido para Bairro / Jd. Sumaré","departure":"12:15:00","tripSeq":1},{"routeId":13398,"tripShortName":"Sentido para Bairro / Jd. Sumaré","tripId":46778,"tripName":"Sentido para Bairro / Jd. Sumaré","departure":"13:25:00","tripSeq":1},{"routeId":13398,"tripShortName":"Sentido para Bairro / Jd. Sumaré","tripId":46778,"tripName":"Sentido para Bairro / Jd. Sumaré","departure":"14:35:00","tripSeq":1},{"routeId":13398,"tripShortName":"Sentido para Bairro / Jd. Sumaré","tripId":46778,"tripName":"Sentido para Bairro / Jd. Sumaré","departure":"15:45:00","tripSeq":1},{"routeId":13398,"tripShortName":"Sentido para Bairro / Jd. Sumaré","tripId":46778,"tripName":"Sentido para Bairro / Jd. Sumaré","departure":"16:55:00","tripSeq":1},{"routeId":13398,"tripShortName":"Sentido para Bairro / Jd. Sumaré","tripId":46778,"tripName":"Sentido para Bairro / Jd. Sumaré","departure":"18:05:00","tripSeq":1},{"routeId":13398,"tripShortName":"Sentido para Bairro / Jd. Sumaré","tripId":46778,"tripName":"Sentido para Bairro / Jd. Sumaré","departure":"19:15:00","tripSeq":1},{"routeId":13398,"tripShortName":"Sentido para Bairro / Jd. Sumaré","tripId":46778,"tripName":"Sentido para Bairro / Jd. Sumaré","departure":"20:25:00","tripSeq":1},{"routeId":13398,"tripShortName":"Sentido para Bairro / Jd. Sumaré","tripId":46778,"tripName":"Sentido para Bairro / Jd. Sumaré","departure":"21:30:00","tripSeq":1},{"routeId":13398,"tripShortName":"Sentido para Bairro / Jd. Sumaré","tripId":46778,"tripName":"Sentido para Bairro / Jd. Sumaré","departure":"22:30:00","tripSeq":1},{"routeId":13398,"tripShortName":"Sentido para Bairro / Jd. Sumaré","tripId":46778,"tripName":"Sentido para Bairro / Jd. Sumaré","departure":"23:30:00","tripSeq":1}]},{"serviceId":1072,"serviceDesc":"Domingos/Feriados","departures":[{"routeId":13398,"tripShortName":"Sentido para Bairro / Jd. Sumaré","tripId":46778,"tripName":"Sentido para Bairro / Jd. Sumaré","departure":"06:25:00","tripSeq":1},{"routeId":13398,"tripShortName":"Sentido para Bairro / Jd. Sumaré","tripId":46778,"tripName":"Sentido para Bairro / Jd. Sumaré","departure":"07:35:00","tripSeq":1},{"routeId":13398,"tripShortName":"Sentido para Bairro / Jd. Sumaré","tripId":46778,"tripName":"Sentido para Bairro / Jd. Sumaré","departure":"08:45:00","tripSeq":1},{"routeId":13398,"tripShortName":"Sentido para Bairro / Jd. Sumaré","tripId":46778,"tripName":"Sentido para Bairro / Jd. Sumaré","departure":"09:55:00","tripSeq":1},{"routeId":13398,"tripShortName":"Sentido para Bairro / Jd. Sumaré","tripId":46778,"tripName":"Sentido para Bairro / Jd. Sumaré","departure":"11:05:00","tripSeq":1},{"routeId":13398,"tripShortName":"Sentido para Bairro / Jd. Sumaré","tripId":46778,"tripName":"Sentido para Bairro / Jd. Sumaré","departure":"12:15:00","tripSeq":1},{"routeId":13398,"tripShortName":"Sentido para Bairro / Jd. Sumaré","tripId":46778,"tripName":"Sentido para Bairro / Jd. Sumaré","departure":"13:25:00","tripSeq":1},{"routeId":13398,"tripShortName":"Sentido para Bairro / Jd. Sumaré","tripId":46778,"tripName":"Sentido para Bairro / Jd. Sumaré","departure":"14:35:00","tripSeq":1},{"routeId":13398,"tripShortName":"Sentido para Bairro / Jd. Sumaré","tripId":46778,"tripName":"Sentido para Bairro / Jd. Sumaré","departure":"15:45:00","tripSeq":1},{"routeId":13398,"tripShortName":"Sentido para Bairro / Jd. Sumaré","tripId":46778,"tripName":"Sentido para Bairro / Jd. Sumaré","departure":"16:55:00","tripSeq":1},{"routeId":13398,"tripShortName":"Sentido para Bairro / Jd. Sumaré","tripId":46778,"tripName":"Sentido para Bairro / Jd. Sumaré","departure":"18:05:00","tripSeq":1},{"routeId":13398,"tripShortName":"Sentido para Bairro / Jd. Sumaré","tripId":46778,"tripName":"Sentido para Bairro / Jd. Sumaré","departure":"19:15:00","tripSeq":1},{"routeId":13398,"tripShortName":"Sentido para Bairro / Jd. Sumaré","tripId":46778,"tripName":"Sentido para Bairro / Jd. Sumaré","departure":"20:25:00","tripSeq":1},{"routeId":13398,"tripShortName":"Sentido para Bairro / Jd. Sumaré","tripId":46778,"tripName":"Sentido para Bairro / Jd. Sumaré","departure":"21:30:00","tripSeq":1},{"routeId":13398,"tripShortName":"Sentido para Bairro / Jd. Sumaré","tripId":46778,"tripName":"Sentido para Bairro / Jd. Sumaré","departure":"22:30:00","tripSeq":1},{"routeId":13398,"tripShortName":"Sentido para Bairro / Jd. Sumaré","tripId":46778,"tripName":"Sentido para Bairro / Jd. Sumaré","departure":"23:30:00","tripSeq":1}]}]},{"directionId":1,"directionDesc":"Volta","calendars":[{"serviceId":1073,"serviceDesc":"Dias Úteis","departures":[{"routeId":13398,"tripShortName":"Sentido para Terminal","tripId":46777,"tripName":"Sentido para Terminal","departure":"05:50:00","tripSeq":2},{"routeId":13398,"tripShortName":"Sentido para Terminal","tripId":46777,"tripName":"Sentido para Terminal","departure":"06:20:00","tripSeq":2},{"routeId":13398,"tripShortName":"Sentido para Terminal","tripId":46777,"tripName":"Sentido para Terminal","departure":"06:50:00","tripSeq":2},{"routeId":13398,"tripShortName":"Sentido para Terminal","tripId":46777,"tripName":"Sentido para Terminal","departure":"07:00:00","tripSeq":2},{"routeId":13398,"tripShortName":"Sentido para Terminal","tripId":46777,"tripName":"Sentido para Terminal","departure":"07:30:00","tripSeq":2},{"routeId":13398,"tripShortName":"Sentido para Terminal","tripId":46777,"tripName":"Sentido para Terminal","departure":"08:10:00","tripSeq":2},{"routeId":13398,"tripShortName":"Sentido para Terminal","tripId":46777,"tripName":"Sentido para Terminal","departure":"09:20:00","tripSeq":2},{"routeId":13398,"tripShortName":"Sentido para Terminal","tripId":46777,"tripName":"Sentido para Terminal","departure":"10:30:00","tripSeq":2},{"routeId":13398,"tripShortName":"Sentido para Terminal","tripId":46777,"tripName":"Sentido para Terminal","departure":"11:05:00","tripSeq":2},{"routeId":13398,"tripShortName":"Sentido para Terminal","tripId":46777,"tripName":"Sentido para Terminal","departure":"11:40:00","tripSeq":2},{"routeId":13398,"tripShortName":"Sentido para Terminal","tripId":46777,"tripName":"Sentido para Terminal","departure":"12:15:00","tripSeq":2},{"routeId":13398,"tripShortName":"Sentido para Terminal","tripId":46777,"tripName":"Sentido para Terminal","departure":"12:50:00","tripSeq":2},{"routeId":13398,"tripShortName":"Sentido para Terminal","tripId":46777,"tripName":"Sentido para Terminal","departure":"14:00:00","tripSeq":2},{"routeId":13398,"tripShortName":"Sentido para Terminal","tripId":46777,"tripName":"Sentido para Terminal","departure":"15:10:00","tripSeq":2},{"routeId":13398,"tripShortName":"Sentido para Terminal","tripId":46777,"tripName":"Sentido para Terminal","departure":"16:20:00","tripSeq":2},{"routeId":13398,"tripShortName":"Sentido para Terminal","tripId":46777,"tripName":"Sentido para Terminal","departure":"17:30:00","tripSeq":2},{"routeId":13398,"tripShortName":"Sentido para Terminal","tripId":46777,"tripName":"Sentido para Terminal","departure":"18:10:00","tripSeq":2},{"routeId":13398,"tripShortName":"Sentido para Terminal","tripId":46777,"tripName":"Sentido para Terminal","departure":"18:40:00","tripSeq":2},{"routeId":13398,"tripShortName":"Sentido para Terminal","tripId":46777,"tripName":"Sentido para Terminal","departure":"19:50:00","tripSeq":2},{"routeId":13398,"tripShortName":"Sentido para Terminal","tripId":46777,"tripName":"Sentido para Terminal","departure":"21:00:00","tripSeq":2},{"routeId":13398,"tripShortName":"Sentido para Terminal","tripId":46777,"tripName":"Sentido para Terminal","departure":"22:00:00","tripSeq":2},{"routeId":13398,"tripShortName":"Sentido para Terminal","tripId":46777,"tripName":"Sentido para Terminal","departure":"23:00:00","tripSeq":2}]},{"serviceId":1079,"serviceDesc":"Sábados","departures":[{"routeId":13398,"tripShortName":"Sentido para Terminal","tripId":46777,"tripName":"Sentido para Terminal","departure":"05:50:00","tripSeq":2},{"routeId":13398,"tripShortName":"Sentido para Terminal","tripId":46777,"tripName":"Sentido para Terminal","departure":"06:25:00","tripSeq":2},{"routeId":13398,"tripShortName":"Sentido para Terminal","tripId":46777,"tripName":"Sentido para Terminal","departure":"07:00:00","tripSeq":2},{"routeId":13398,"tripShortName":"Sentido para Terminal","tripId":46777,"tripName":"Sentido para Terminal","departure":"07:35:00","tripSeq":2},{"routeId":13398,"tripShortName":"Sentido para Terminal","tripId":46777,"tripName":"Sentido para Terminal","departure":"08:10:00","tripSeq":2},{"routeId":13398,"tripShortName":"Sentido para Terminal","tripId":46777,"tripName":"Sentido para Terminal","departure":"09:20:00","tripSeq":2},{"routeId":13398,"tripShortName":"Sentido para Terminal","tripId":46777,"tripName":"Sentido para Terminal","departure":"10:30:00","tripSeq":2},{"routeId":13398,"tripShortName":"Sentido para Terminal","tripId":46777,"tripName":"Sentido para Terminal","departure":"11:05:00","tripSeq":2},{"routeId":13398,"tripShortName":"Sentido para Terminal","tripId":46777,"tripName":"Sentido para Terminal","departure":"11:40:00","tripSeq":2},{"routeId":13398,"tripShortName":"Sentido para Terminal","tripId":46777,"tripName":"Sentido para Terminal","departure":"12:15:00","tripSeq":2},{"routeId":13398,"tripShortName":"Sentido para Terminal","tripId":46777,"tripName":"Sentido para Terminal","departure":"12:50:00","tripSeq":2},{"routeId":13398,"tripShortName":"Sentido para Terminal","tripId":46777,"tripName":"Sentido para Terminal","departure":"14:00:00","tripSeq":2},{"routeId":13398,"tripShortName":"Sentido para Terminal","tripId":46777,"tripName":"Sentido para Terminal","departure":"15:10:00","tripSeq":2},{"routeId":13398,"tripShortName":"Sentido para Terminal","tripId":46777,"tripName":"Sentido para Terminal","departure":"16:20:00","tripSeq":2},{"routeId":13398,"tripShortName":"Sentido para Terminal","tripId":46777,"tripName":"Sentido para Terminal","departure":"17:30:00","tripSeq":2},{"routeId":13398,"tripShortName":"Sentido para Terminal","tripId":46777,"tripName":"Sentido para Terminal","departure":"18:40:00","tripSeq":2},{"routeId":13398,"tripShortName":"Sentido para Terminal","tripId":46777,"tripName":"Sentido para Terminal","departure":"19:50:00","tripSeq":2},{"routeId":13398,"tripShortName":"Sentido para Terminal","tripId":46777,"tripName":"Sentido para Terminal","departure":"21:00:00","tripSeq":2},{"routeId":13398,"tripShortName":"Sentido para Terminal","tripId":46777,"tripName":"Sentido para Terminal","departure":"22:00:00","tripSeq":2},{"routeId":13398,"tripShortName":"Sentido para Terminal","tripId":46777,"tripName":"Sentido para Terminal","departure":"23:00:00","tripSeq":2}]},{"serviceId":1072,"serviceDesc":"Domingos/Feriados","departures":[{"routeId":13398,"tripShortName":"Sentido para Terminal","tripId":46777,"tripName":"Sentido para Terminal","departure":"05:50:00","tripSeq":2},{"routeId":13398,"tripShortName":"Sentido para Terminal","tripId":46777,"tripName":"Sentido para Terminal","departure":"07:00:00","tripSeq":2},{"routeId":13398,"tripShortName":"Sentido para Terminal","tripId":46777,"tripName":"Sentido para Terminal","departure":"08:10:00","tripSeq":2},{"routeId":13398,"tripShortName":"Sentido para Terminal","tripId":46777,"tripName":"Sentido para Terminal","departure":"09:20:00","tripSeq":2},{"routeId":13398,"tripShortName":"Sentido para Terminal","tripId":46777,"tripName":"Sentido para Terminal","departure":"10:30:00","tripSeq":2},{"routeId":13398,"tripShortName":"Sentido para Terminal","tripId":46777,"tripName":"Sentido para Terminal","departure":"11:40:00","tripSeq":2},{"routeId":13398,"tripShortName":"Sentido para Terminal","tripId":46777,"tripName":"Sentido para Terminal","departure":"12:50:00","tripSeq":2},{"routeId":13398,"tripShortName":"Sentido para Terminal","tripId":46777,"tripName":"Sentido para Terminal","departure":"14:00:00","tripSeq":2},{"routeId":13398,"tripShortName":"Sentido para Terminal","tripId":46777,"tripName":"Sentido para Terminal","departure":"15:10:00","tripSeq":2},{"routeId":13398,"tripShortName":"Sentido para Terminal","tripId":46777,"tripName":"Sentido para Terminal","departure":"16:20:00","tripSeq":2},{"routeId":13398,"tripShortName":"Sentido para Terminal","tripId":46777,"tripName":"Sentido para Terminal","departure":"17:30:00","tripSeq":2},{"routeId":13398,"tripShortName":"Sentido para Terminal","tripId":46777,"tripName":"Sentido para Terminal","departure":"18:40:00","tripSeq":2},{"routeId":13398,"tripShortName":"Sentido para Terminal","tripId":46777,"tripName":"Sentido para Terminal","departure":"19:50:00","tripSeq":2},{"routeId":13398,"tripShortName":"Sentido para Terminal","tripId":46777,"tripName":"Sentido para Terminal","departure":"21:00:00","tripSeq":2},{"routeId":13398,"tripShortName":"Sentido para Terminal","tripId":46777,"tripName":"Sentido para Terminal","departure":"22:00:00","tripSeq":2},{"routeId":13398,"tripShortName":"Sentido para Terminal","tripId":46777,"tripName":"Sentido para Terminal","departure":"23:00:00","tripSeq":2}]}]}],"trips":[{"tripDesc":"Sentido para Terminal","tripShortName":null,"directionId":1,"tripSeq":2},{"tripDesc":"Sentido para Bairro / Jd. Sumaré","tripShortName":null,"directionId":0,"tripSeq":1}],"routes":null,"note":null}